piston/admin.py
piston/authentication.py
piston/decorator.py
piston/doc.py
piston/emitters.py
piston/forms.py
piston/handler.py
piston/handlers_doc.py
piston/managers.py
piston/middleware.py
piston/models.py
piston/oauth.py
piston/resource.py
piston/signals.py
piston/store.py
piston/test.py
piston/tests.py
piston/utils.py
piston/validate_jsonp.py
piston/migrations/0001_initial.py
piston/migrations/__init__.py
piston/templates/documentation.html
piston/templates/piston/authorize_token.html
django_piston_citadel-0.3.0.dist-info/LICENSE
django_piston_citadel-0.3.0.dist-info/METADATA
django_piston_citadel-0.3.0.dist-info/WHEEL
django_piston_citadel-0.3.0.dist-info/top_level.txt
django_piston_citadel-0.3.0.dist-info/RECORD
