Metadata-Version: 2.1
Name: django-piston-citadel
Version: 0.3.0
Summary: Piston is a Django mini-framework creating APIs.
Author-email: Jesper Noehr <jesper@noehr.org>
Project-URL: Homepage, http://bitbucket.org/jespern/django-piston/wiki/Home
Project-URL: Download, http://bitbucket.org/jespern/django-piston/downloads/
Classifier: Programming Language :: Python :: 3
Classifier: License :: OSI Approved :: BSD License
Classifier: Operating System :: OS Independent
Classifier: Development Status :: 3 - Alpha
Classifier: Intended Audience :: Developers
Classifier: Framework :: Django
Classifier: Programming Language :: Python
Classifier: Topic :: Internet :: WWW/HTTP
Requires-Python: >=3.6
License-File: LICENSE
